setup.py
nret/FourSAIL.py
nret/__init__.py
nret/fAPAR.py
nret/licence.txt
nret/light_spectra.txt
nret/prosail_input_gen.py
nret/prospect5_spectra.txt
nret/prospect_d.py
nret/prospect_d_spectra.txt
nret/prospect_pro_spectra.txt
nret/sail_model.py
nret/simulate_df.py
nret/soil_reflectance.txt
nret/spectral_library.py
nret.egg-info/PKG-INFO
nret.egg-info/SOURCES.txt
nret.egg-info/dependency_links.txt
nret.egg-info/not-zip-safe
nret.egg-info/requires.txt
nret.egg-info/top_level.txt