Metadata-Version: 2.1
Name: nret
Version: 0.1
Summary: A Python module that contains all the tools neeeded for retrieving N concentration from satellite bands
Home-page: https://github.com/Mahmoud-H97/NRET
Author: Mahmoud H. Ahmed  @ IHE Delft, The Netherlands
Author-email: mahmoudhatim55@gmail.com
License: UNKNOWN
Platform: UNKNOWN
